anyfig/__init__.py
anyfig/anyfig_setup.py
anyfig/config_functions.py
anyfig/dummyfields.py
anyfig/fields.py
anyfig/figutils.py
anyfig/print_utils.py
anyfig-0.2.0.dist-info/AUTHORS.MD
anyfig-0.2.0.dist-info/LICENSE
anyfig-0.2.0.dist-info/METADATA
anyfig-0.2.0.dist-info/WHEEL
anyfig-0.2.0.dist-info/top_level.txt
anyfig-0.2.0.dist-info/RECORD
