Metadata-Version: 2.1
Name: anyfig
Version: 0.2.0
Summary: Create modular and scaleable configurations at runtime
Home-page: https://github.com/OlofHarrysson/anyfig
Author: Olof Harrysson
Author-email: harrysson.olof@gmail.com
License: MIT license
Keywords: config,configurations,configuration-management,argparse-alternative,settings,command line parsing,python classes,dynamic,runtime
Platform: UNKNOWN
Classifier: Development Status :: 2 - Pre-Alpha
Classifier: Intended Audience :: Developers
Classifier: Topic :: Software Development :: Build Tools
Classifier: License :: OSI Approved :: MIT License
Classifier: Natural Language :: English
Classifier: Programming Language :: Python :: 3
Classifier: Programming Language :: Python :: 3.6
Classifier: Programming Language :: Python :: 3.7
Classifier: Programming Language :: Python :: 3.8
Requires-Python: >=3.6
Requires-Dist: fire
Requires-Dist: typeguard
Requires-Dist: dill
Requires-Dist: dataclasses ; python_version == "3.6"
